asciinema_director/__init__.py
asciinema_director/__main__.py
asciinema_director/cli.py
asciinema_director/director.py
asciinema_director-0.1.1.dist-info/entry_points.txt
asciinema_director-0.1.1.dist-info/WHEEL
asciinema_director-0.1.1.dist-info/METADATA
asciinema_director-0.1.1.dist-info/RECORD
